{
    "1391613050": {
        "created": 110,
        "fix_committed": 7,
        "in_progress": 3
    },
    "1392217850": {
        "created": 111,
        "fix_committed": 7,
        "in_progress": 3
    },
    "1392822650": {
        "created": 112,
        "fix_committed": 8,
        "in_progress": 3
    },
    "1393427450": {
        "created": 114,
        "fix_committed": 10,
        "in_progress": 1
    },
    "1394032250": {
        "created": 115,
        "fix_committed": 10,
        "in_progress": 1
    },
    "1394637050": {
        "created": 114,
        "fix_committed": 10,
        "in_progress": 2
    },
    "1395241850": {
        "created": 115,
        "fix_committed": 11,
        "in_progress": 3
    },
    "1395846650": {
        "created": 117,
        "fix_committed": 11,
        "in_progress": 3
    },
    "1396451450": {
        "created": 117,
        "fix_committed": 11,
        "in_progress": 3
    },
    "1397056250": {
        "created": 121,
        "fix_committed": 11,
        "in_progress": 4
    },
    "1397661050": {
        "created": 119,
        "fix_committed": 11,
        "in_progress": 8
    },
    "1398265850": {
        "created": 122,
        "fix_committed": 12,
        "in_progress": 8
    },
    "1398870650": {
        "created": 126,
        "fix_committed": 22,
        "in_progress": 8
    },
    "1399475450": {
        "created": 120,
        "fix_committed": 22,
        "in_progress": 15
    },
    "1400080250": {
        "created": 122,
        "fix_committed": 22,
        "in_progress": 15
    },
    "1400685050": {
        "created": 123,
        "fix_committed": 22,
        "in_progress": 16
    },
    "1401289850": {
        "created": 131,
        "fix_committed": 24,
        "in_progress": 15
    },
    "1401894650": {
        "created": 132,
        "fix_committed": 27,
        "in_progress": 15
    },
    "1402499450": {
        "created": 134,
        "fix_committed": 29,
        "in_progress": 13
    },
    "1403104250": {
        "created": 135,
        "fix_committed": 30,
        "in_progress": 13
    },
    "1403709050": {
        "created": 141,
        "fix_committed": 32,
        "in_progress": 14
    },
    "1404313850": {
        "created": 141,
        "fix_committed": 33,
        "in_progress": 15
    },
    "1404918650": {
        "created": 142,
        "fix_committed": 43,
        "in_progress": 13
    },
    "1405523450": {
        "created": 143,
        "fix_committed": 44,
        "in_progress": 13
    },
    "1406128250": {
        "created": 151,
        "fix_committed": 47,
        "in_progress": 15
    },
    "1406733050": {
        "created": 149,
        "fix_committed": 50,
        "in_progress": 24
    },
    "1407337850": {
        "created": 154,
        "fix_committed": 53,
        "in_progress": 26
    },
    "1407942650": {
        "fix_committed": 70,
        "in_progress": 31,
        "created": 160
    },
    "1408547450": {
        "fix_committed": 78,
        "in_progress": 32,
        "created": 171
    },
    "1409152250": {
        "fix_committed": 89,
        "in_progress": 37,
        "created": 175
    },
    "1409757050": {
        "fix_committed": 116,
        "in_progress": 37,
        "created": 166
    },
    "1410361850": {
        "fix_committed": 132,
        "in_progress": 37,
        "created": 162
    },
    "1410966650": {
        "fix_committed": 136,
        "in_progress": 37,
        "created": 166
    },
    "1411571450": {
        "fix_committed": 144,
        "in_progress": 47,
        "created": 149
    },
    "1412176250": {
        "fix_committed": 156,
        "in_progress": 49,
        "created": 139
    },
    "1412781050": {
        "fix_committed": 194,
        "created": 129,
        "in_progress": 34
    },
    "1413385850": {
        "fix_committed": 205,
        "created": 119,
        "in_progress": 39
    },
    "1413990650": {
        "fix_committed": 229,
        "in_progress": 35,
        "created": 110
    },
    "1414595450": {
        "fix_committed": 237,
        "in_progress": 39,
        "created": 106
    },
    "1415200250": {
        "fix_committed": 254,
        "in_progress": 45,
        "created": 87
    },
    "1415805050": {
        "fix_committed": 280,
        "in_progress": 37,
        "created": 75
    },
    "1416409850": {
        "fix_committed": 289,
        "in_progress": 38,
        "created": 79
    },
    "1417014650": {
        "fix_committed": 324,
        "in_progress": 15,
        "created": 75
    },
    "1417619450": {
        "fix_committed": 336,
        "in_progress": 17,
        "created": 67
    },
    "1418224250": {
        "fix_committed": 348,
        "created": 69,
        "in_progress": 14
    },
    "1418829050": {
        "fix_committed": 372,
        "in_progress": 15,
        "created": 53
    },
    "1419433850": {
        "fix_committed": 386,
        "in_progress": 17,
        "created": 43
    },
    "1420038650": {
        "fix_committed": 420,
        "in_progress": 14,
        "created": 23
    },
    "1420643450": {
        "fix_committed": 433,
        "in_progress": 14,
        "created": 13
    },
    "1421248250": {
        "fix_committed": 437,
        "in_progress": 14,
        "created": 11
    },
    "1421853050": {
        "fix_committed": 454,
        "in_progress": 7,
        "created": 5
    },
    "1422457850": {
        "fix_committed": 464,
        "in_progress": 3
    }
}