{
    "Whoops! That link has expired.": "¡Vaya! Este enlace ha caducado.",
    "If you’re trying to download elementary OS, please head back to <a href=\"/\">the home page</a> for the most up-to-date version. If you were brought here from a third-party website, it is possible they were attempting to bypass the payment prompt or installation directions. Please inform them that download links are temporary, per-user, and load-balanced. The correct way to link to the download is to link to <a href=\"https://elementary.io\">elementary.io</a>.": "Si estás intentando descargar elementary OS, por favor vuelve a <a href=\"/\">la página principal</a> para obtener la última versión. Si llegaste aquí a través de una web de un tercero, es posible que estuviesen intentando evitar la pantalla de pago o las direcciones de instalación. En ese caso, por favor, infórmales de que los enlaces de descarga son temporales, individuales para cada usuario y con la carga distribuida. La manera correcta de enlazar a la descarga es apuntando a <a href=\"https://elementary.io\">elementary.io</a>.",
    "If you were looking for something else, feel free to <a href=\"https://github.com/elementary/website/issues/new\">file an issue on our GitHub</a>.": "Si estabas buscando otra cosa, puedes  <a href=\"https://github.com/elementary/website/issues/new\">añadir una \"issue\" en nuestro GitHub</a>.",
    "Go to Home Page": "Ir a la página principal",
    "Download Link Expired &sdot; elementary": "El enlace de descarga caducó &sdot; elementary"
}
