{
    "A fast and open replacement for Windows and macOS &sdot; elementary OS": "一个快速的、开放的、可替代 Windows 和 macOS 的操作系统——elementary OS",
    "Support": "支持",
    "Developer": "开发者",
    "Get Involved": "参与其中",
    "Store": "商店",
    "This is a development site.": "网站开发中",
    "You are viewing a development version of our site. Some pages here may not work or act as you expect. If you got here by accident please go to <a href=\"http://elementary.io\">elementary.io</a>, our actual website address.": "您正在访问开发中的网站版本。部分页面可能无法如您的预期运行。如果您意外访问这里，请您前往<a href=\"http://elementary.io\">elementary.io</a>，我们实际的网站地址。",
    "Copyright &copy; 2017 elementary LLC.": "Copyright © 2017 elementary LLC.",
    "Language": "语言",
    "Change Site Language": "修改网站语言",
    "Brand": "品牌",
    "Privacy Policy": "隐私政策",
    "Team": "Team",
    "Open Source": "开源"
}