{
    "Get support for": "सहायता प्राप्त करें",
    "Calendar": "केलेंडर",
    "Camera": "कैमरा",
    "Files": "फ़ाइलें",
    "Geary": "Geary",
    "Epiphany": "Epiphany",
    "Music": "संगीत",
    "Photos": "तस्वीरें",
    "Text Editor": "टेक्स्ट एडिटर",
    "System Settings": "सिस्टम सेटिंग",
    "Videos": "वीडियो",
    "Installation": "स्थापना",
    "Get help installing elementary OS with our step-by-step guide.": "एलीमेंट्री ओएस के इंस्टॉलिंग को लेकर मदद के लिए हमारे स्टेप-बाई-स्टेप गाइड की सहायता लें. ",
    "Learning the Basics": "बेसिक्स सीखें ",
    "Walk through the desktop, multi-tasking, keyboard shortcuts and more.": "Walk through the desktop, multi-tasking, keyboard shortcuts and more.",
    "StackExchange": "स्टैक एक्सचेंज",
    "Check out answers to some of the most common questions we get.": "Check out answers to some of the most common questions we get.",
    "Support &sdot; elementary": "सहायता ⋅ elementary"
}