{
    "Get Support": "Dapatkan Dukungan",
    "We rely on our <a href=\"https://elementaryos.stackexchange.com\" target=\"_blank\" rel=\"noopener\">community-powered Stack Exchange</a> for support. Search for common questions, ask your own, or help out by answering some. Pick an app below to jump to questions about it specifically.": "Kami mengandalkan <a href=\"https://elementaryos.stackexchange.com\" target=\"_blank\" rel=\"noopener\"> Stack Exchange yang diberdayakan oleh komunitas </a> kami untuk mendapatkan dukungan. Telusuri pertanyaan umum, tanyakan pertanyaan Anda sendiri, atau bantu dengan menjawab beberapa. Pilih aplikasi di bawah ini untuk menjawab pertanyaan tentangnya secara spesifik.",
    "AppCenter": "AppCenter",
    "Calendar": "Kalender",
    "Camera": "Kamera",
    "Files": "Berkas",
    "Mail": "Surat",
    "Epiphany": "Epiphany",
    "Music": "Musik",
    "Photos": "Foto",
    "Code": "Kode",
    "System Settings": "Pengaturan Sistem",
    "Videos": "Video",
    "Guides": "Panduan",
    "Installation": "Instalasi",
    "Get help installing elementary OS with our step-by-step guide.": "Dapatkan bantuan menginstal elementary OS dengan panduan langkah-demi-langkah kami.",
    "Learning the Basics": "Pelajari Dasar-Dasar",
    "Walk through the desktop, multi-tasking, keyboard shortcuts and more.": "Jelajahi desktop, panca tugas, pintasan papan ketik, dan banyak lagi.",
    "Support &sdot; elementary": "Dukungan &sdot; elementary"
}
