{
    "Get support for": "احصل علي الدعم لل",
    "Calendar": "التقويم",
    "Camera": "الكاميرا",
    "Files": "الملفات",
    "Geary": "جيري",
    "Epiphany": "",
    "Music": "الموسيقي",
    "Photos": "الصور",
    "Text Editor": "",
    "System Settings": "إعدادات النظام",
    "Videos": "الفيديوهات",
    "Installation": "التثبيت",
    "Get help installing elementary OS with our step-by-step guide.": "",
    "Learning the Basics": "",
    "Walk through the desktop, multi-tasking, keyboard shortcuts and more.": "",
    "StackExchange": "",
    "Check out answers to some of the most common questions we get.": "",
    "Support ⋅ elementary": ""
}