{
    "A fast and open replacement for Windows and macOS &sdot; elementary OS": "Hệ điều hành mở và rất nhanh, có thể thay thế cho Windows và macOS ⋅ elementary OS",
    "Blog": "Blog",
    "Support": "Hỗ trợ",
    "Store": "Cửa hàng",
    "Developer": "Nhà phát triển Ứng dụng",
    "Get Involved": "Tham gia cùng chúng tôi",
    "This is a development site.": "Đây là một trang web đang được phát triển.",
    "You are viewing a development version of our site. Some pages here may not work or act as you expect. If you got here by accident please go to <a href=\"http://elementary.io\">elementary.io</a>, our actual website address.": "Bạn đang xem phiên bản thử nghiệm của trang web của chúng tôi. Một vài trang ở đây có thể không thực thi như bạn mong muốn. Nếu bạn đến trang này một cách tình cờ, vui lòng chuyển tới <a href=\"http://elementary.io\">elementary.io</a>, hoặc trang web thực sự của chúng tôi.",
    "Copyright &copy; 2016 elementary LLC.\n                    <a href=\"/team\">Team</a>\n                    <a href=\"/brand\">Brand</a>\n                    <a href=\"/privacy-policy\">Privacy Policy</a>": "Copyright © 2016 elementary LLC.\n                    <a href=\"/team\">Team</a>\n                    <a href=\"/brand\">Brand</a>\n                    <a href=\"/privacy-policy\">Privacy Policy</a>",
    "Language": "Ngôn ngữ",
    "Change Site Language": "Thay đổi ngôn ngữ"
}